pyhap/accessories/maxcube/__init__.py
pyhap_maxcube-0.5.dist-info/LICENSE
pyhap_maxcube-0.5.dist-info/METADATA
pyhap_maxcube-0.5.dist-info/WHEEL
pyhap_maxcube-0.5.dist-info/top_level.txt
pyhap_maxcube-0.5.dist-info/RECORD
