Metadata-Version: 2.1
Name: pyhap-maxcube
Version: 0.5
Summary: HAP-python Accessories for e-Q3 MAX! devices.
Home-page: https://github.com/ikalchev/pyhap-maxcube
Author: Ivan Kalchev
License: Apache-2.0
Platform: UNKNOWN
Classifier: Development Status :: 4 - Beta
Classifier: Programming Language :: Python :: 3
Classifier: Topic :: Home Automation
Classifier: Topic :: Software Development :: Libraries :: Python Modules
Classifier: License :: OSI Approved :: Apache Software License
Classifier: Intended Audience :: Developers
Requires-Dist: HAP-python (>=2.0.0)
Requires-Dist: maxcube-api (>=0.1.0)
